qdrant_manager/__init__.py
qdrant_manager/cli.py
qdrant_manager/config.py
qdrant_manager/utils.py
qdrant_manager/commands/__init__.py
qdrant_manager/commands/batch.py
qdrant_manager/commands/create.py
qdrant_manager/commands/delete.py
qdrant_manager/commands/get.py
qdrant_manager/commands/info.py
qdrant_manager/commands/list_cmd.py
qdrant_manager-0.1.6.dist-info/licenses/LICENSE
qdrant_manager-0.1.6.dist-info/METADATA
qdrant_manager-0.1.6.dist-info/WHEEL
qdrant_manager-0.1.6.dist-info/entry_points.txt
qdrant_manager-0.1.6.dist-info/top_level.txt
qdrant_manager-0.1.6.dist-info/RECORD
