Metadata-Version: 2.4
Name: qdrant-manager
Version: 0.1.6
Summary: Command-line tool for managing Qdrant vector database collections
Home-page: https://github.com/allenday/qdrant-manager
Author: Allen Day
Author-email: Allen Day <allenday@example.com>
License: Apache-2.0
Project-URL: Homepage, https://github.com/allenday/qdrant-manager
Project-URL: Bug Reports, https://github.com/allenday/qdrant-manager/issues
Classifier: Development Status :: 4 - Beta
Classifier: Intended Audience :: Developers
Classifier: License :: OSI Approved :: Apache Software License
Classifier: Programming Language :: Python :: 3
Classifier: Programming Language :: Python :: 3.8
Classifier: Programming Language :: Python :: 3.9
Classifier: Programming Language :: Python :: 3.10
Requires-Python: >=3.8
License-File: LICENSE
Requires-Dist: qdrant-client>=1.7.0
Requires-Dist: tqdm>=4.66.0
Requires-Dist: pyyaml>=6.0
Requires-Dist: appdirs>=1.4.4
Provides-Extra: dev
Requires-Dist: pytest>=6.0.0; extra == "dev"
Requires-Dist: pytest-cov>=6.0.0; extra == "dev"
Dynamic: author
Dynamic: home-page
Dynamic: license-file
Dynamic: requires-python
